{
  "v": "5.9.0",
  "fr": 30,
  "ip": 0,
  "op": 60,
  "w": 500,
  "h": 500,
  "nm": "4",
  "assets": [],
  "layers": [
    {
      "ind": 1,
      "ty": 3,
      "nm": "N",
      "sr": 1,
      "ks": {
        "o": { "a": 0, "k": 0 },
        "r": { "a": 0, "k": 0 },
        "p": { "a": 0, "k": [250, 250, 0], "l": 2 },
        "a": { "a": 0, "k": [50, 50, 0], "l": 2 },
        "s": { "a": 0, "k": [500, 500, 100], "l": 2 }
      },
      "ao": 0,
      "ip": 0,
      "op": 90,
      "st": 0
    },
    {
      "ind": 2,
      "ty": 3,
      "nm": "b",
      "sr": 1,
      "ks": {
        "o": { "a": 0, "k": 0 },
        "r": { "a": 0, "k": 0 },
        "p": { "a": 0, "k": [252, 280.75, 0], "l": 2 },
        "a": { "a": 0, "k": [0, 0, 0], "l": 2 },
        "s": { "a": 0, "k": [100, 100, 100], "l": 2 }
      },
      "ao": 0,
      "ip": 0,
      "op": 90,
      "st": 0
    },
    {
      "ind": 3,
      "ty": 4,
      "nm": "s",
      "parent": 7,
      "sr": 1,
      "ks": {
        "o": { "a": 0, "k": 100 },
        "r": {
          "a": 1,
          "k": [
            {
              "i": { "x": [0.833], "y": [0.833] },
              "o": { "x": [0.167], "y": [0.167] },
              "t": 0,
              "s": [0]
            },
            { "t": 60, "s": [720] }
          ]
        },
        "p": { "a": 0, "k": [18.918, 7.673, 0], "l": 2 },
        "a": { "a": 0, "k": [-18.918, 7.673, 0], "l": 2 },
        "s": { "a": 0, "k": [100, 100, 100], "l": 2 }
      },
      "ao": 0,
      "shapes": [
        {
          "ty": "gr",
          "it": [
            {
              "ty": "gr",
              "it": [
                {
                  "ind": 0,
                  "ty": "sh",
                  "ks": {
                    "a": 0,
                    "k": {
                      "i": [
                        [0, -4.594],
                        [4.594, 0],
                        [0, 4.594],
                        [-4.594, 0]
                      ],
                      "o": [
                        [0, 4.594],
                        [-4.594, 0],
                        [0, -4.594],
                        [4.594, 0]
                      ],
                      "v": [
                        [-10.6, 7.673],
                        [-18.918, 15.991],
                        [-27.236, 7.673],
                        [-18.918, -0.645]
                      ],
                      "c": true
                    }
                  },
                  "nm": "P"
                },
                {
                  "ty": "st",
                  "c": { "a": 0, "k": [0.243, 0.204, 0.49, 1] },
                  "o": { "a": 0, "k": 100 },
                  "w": { "a": 0, "k": 0.5 },
                  "lc": 2,
                  "lj": 2,
                  "nm": "S"
                },
                {
                  "ty": "tr",
                  "p": { "a": 0, "k": [0, 0] },
                  "a": { "a": 0, "k": [0, 0] },
                  "s": { "a": 0, "k": [100, 100] },
                  "r": { "a": 0, "k": 0 },
                  "o": { "a": 0, "k": 100 },
                  "sk": { "a": 0, "k": 0 },
                  "sa": { "a": 0, "k": 0 },
                  "nm": "T"
                }
              ],
              "nm": "G"
            },
            {
              "ty": "tr",
              "p": { "a": 0, "k": [0, 0] },
              "a": { "a": 0, "k": [0, 0] },
              "s": { "a": 0, "k": [100, 100] },
              "r": { "a": 0, "k": 0 },
              "o": { "a": 0, "k": 100 },
              "sk": { "a": 0, "k": 0 },
              "sa": { "a": 0, "k": 0 },
              "nm": "T"
            }
          ],
          "nm": "G"
        },
        {
          "ty": "tm",
          "s": { "a": 0, "k": 86 },
          "e": { "a": 0, "k": 100 },
          "o": { "a": 0, "k": 0 },
          "m": 1,
          "nm": "T"
        }
      ],
      "ip": 0,
      "op": 90,
      "st": 0
    },
    {
      "ind": 4,
      "ty": 4,
      "nm": "s",
      "parent": 7,
      "sr": 1,
      "ks": {
        "o": { "a": 0, "k": 100 },
        "r": {
          "a": 1,
          "k": [
            {
              "i": { "x": [0.833], "y": [0.833] },
              "o": { "x": [0.167], "y": [0.167] },
              "t": 0,
              "s": [0]
            },
            { "t": 60, "s": [720] }
          ]
        },
        "p": { "a": 0, "k": [-18.918, 7.673, 0], "l": 2 },
        "a": { "a": 0, "k": [-18.918, 7.673, 0], "l": 2 },
        "s": { "a": 0, "k": [100, 100, 100], "l": 2 }
      },
      "ao": 0,
      "shapes": [
        {
          "ty": "gr",
          "it": [
            {
              "ty": "gr",
              "it": [
                {
                  "ind": 0,
                  "ty": "sh",
                  "ks": {
                    "a": 0,
                    "k": {
                      "i": [
                        [0, -4.594],
                        [4.594, 0],
                        [0, 4.594],
                        [-4.594, 0]
                      ],
                      "o": [
                        [0, 4.594],
                        [-4.594, 0],
                        [0, -4.594],
                        [4.594, 0]
                      ],
                      "v": [
                        [-10.6, 7.673],
                        [-18.918, 15.991],
                        [-27.236, 7.673],
                        [-18.918, -0.645]
                      ],
                      "c": true
                    }
                  },
                  "nm": "P"
                },
                {
                  "ty": "st",
                  "c": { "a": 0, "k": [0.243, 0.204, 0.49, 1] },
                  "o": { "a": 0, "k": 100 },
                  "w": { "a": 0, "k": 0.5 },
                  "lc": 2,
                  "lj": 2,
                  "nm": "S"
                },
                {
                  "ty": "tr",
                  "p": { "a": 0, "k": [0, 0] },
                  "a": { "a": 0, "k": [0, 0] },
                  "s": { "a": 0, "k": [100, 100] },
                  "r": { "a": 0, "k": 0 },
                  "o": { "a": 0, "k": 100 },
                  "sk": { "a": 0, "k": 0 },
                  "sa": { "a": 0, "k": 0 },
                  "nm": "T"
                }
              ],
              "nm": "G"
            },
            {
              "ty": "tr",
              "p": { "a": 0, "k": [0, 0] },
              "a": { "a": 0, "k": [0, 0] },
              "s": { "a": 0, "k": [100, 100] },
              "r": { "a": 0, "k": 0 },
              "o": { "a": 0, "k": 100 },
              "sk": { "a": 0, "k": 0 },
              "sa": { "a": 0, "k": 0 },
              "nm": "T"
            }
          ],
          "nm": "G"
        },
        {
          "ty": "tm",
          "s": { "a": 0, "k": 86 },
          "e": { "a": 0, "k": 100 },
          "o": { "a": 0, "k": 0 },
          "m": 1,
          "nm": "T"
        }
      ],
      "ip": 0,
      "op": 90,
      "st": 0
    },
    {
      "ind": 5,
      "ty": 4,
      "nm": "b",
      "parent": 6,
      "sr": 1,
      "ks": {
        "o": { "a": 0, "k": 100 },
        "r": {
          "a": 1,
          "k": [
            {
              "i": { "x": [0.833], "y": [0.833] },
              "o": { "x": [0.167], "y": [0.167] },
              "t": 0,
              "s": [360]
            },
            { "t": 60, "s": [0] }
          ]
        },
        "p": { "a": 0, "k": [0.52, 14.574, 0], "l": 2 },
        "a": { "a": 0, "k": [0.52, 14.574, 0], "l": 2 },
        "s": { "a": 0, "k": [100, 100, 100], "l": 2 }
      },
      "ao": 0,
      "shapes": [
        {
          "ty": "gr",
          "it": [
            {
              "ty": "gr",
              "it": [
                {
                  "ty": "gr",
                  "it": [
                    {
                      "ind": 0,
                      "ty": "sh",
                      "ks": {
                        "a": 0,
                        "k": {
                          "i": [
                            [0, -0.345],
                            [0, 0],
                            [0.345, 0],
                            [0, 0],
                            [0, 0.358],
                            [0, 0],
                            [-0.345, 0],
                            [0, 0]
                          ],
                          "o": [
                            [0, 0],
                            [0, 0.358],
                            [0, 0],
                            [-0.345, 0],
                            [0, 0],
                            [0, -0.345],
                            [0, 0],
                            [0.345, 0]
                          ],
                          "v": [
                            [3.37, 14.092],
                            [3.37, 15.042],
                            [2.74, 15.684],
                            [-1.701, 15.684],
                            [-2.33, 15.042],
                            [-2.33, 14.092],
                            [-1.701, 13.463],
                            [2.74, 13.463]
                          ],
                          "c": true
                        }
                      },
                      "nm": "P"
                    },
                    {
                      "ty": "st",
                      "c": { "a": 0, "k": [0.243, 0.204, 0.49, 1] },
                      "o": { "a": 0, "k": 100 },
                      "w": { "a": 0, "k": 0.5 },
                      "lc": 2,
                      "lj": 2,
                      "nm": "S"
                    },
                    {
                      "ty": "fl",
                      "c": { "a": 0, "k": [0.949, 0.576, 0.122, 1] },
                      "o": { "a": 0, "k": 100 },
                      "r": 1,
                      "nm": "F"
                    },
                    {
                      "ty": "tr",
                      "p": { "a": 0, "k": [0, 0] },
                      "a": { "a": 0, "k": [0, 0] },
                      "s": { "a": 0, "k": [100, 100] },
                      "r": { "a": 0, "k": 0 },
                      "o": { "a": 0, "k": 100 },
                      "sk": { "a": 0, "k": 0 },
                      "sa": { "a": 0, "k": 0 },
                      "nm": "T"
                    }
                  ],
                  "nm": "G"
                },
                {
                  "ty": "tr",
                  "p": { "a": 0, "k": [0, 0] },
                  "a": { "a": 0, "k": [0, 0] },
                  "s": { "a": 0, "k": [100, 100] },
                  "r": { "a": 0, "k": 0 },
                  "o": { "a": 0, "k": 100 },
                  "sk": { "a": 0, "k": 0 },
                  "sa": { "a": 0, "k": 0 },
                  "nm": "T"
                }
              ],
              "nm": "G"
            },
            {
              "ty": "tr",
              "p": { "a": 0, "k": [0, 0] },
              "a": { "a": 0, "k": [0, 0] },
              "s": { "a": 0, "k": [100, 100] },
              "r": { "a": 0, "k": 0 },
              "o": { "a": 0, "k": 100 },
              "sk": { "a": 0, "k": 0 },
              "sa": { "a": 0, "k": 0 },
              "nm": "T"
            }
          ],
          "nm": "G"
        }
      ],
      "ip": 0,
      "op": 90,
      "st": 0
    },
    {
      "ind": 6,
      "ty": 4,
      "nm": "l",
      "parent": 7,
      "sr": 1,
      "ks": {
        "o": { "a": 0, "k": 100 },
        "r": {
          "a": 1,
          "k": [
            {
              "i": { "x": [0.833], "y": [0.833] },
              "o": { "x": [0.167], "y": [0.167] },
              "t": 0,
              "s": [0]
            },
            { "t": 60, "s": [360] }
          ]
        },
        "p": { "a": 0, "k": [0.52, 7.673, 0], "l": 2 },
        "a": { "a": 0, "k": [0.52, 7.673, 0], "l": 2 },
        "s": { "a": 0, "k": [100, 100, 100], "l": 2 }
      },
      "ao": 0,
      "shapes": [
        {
          "ty": "gr",
          "it": [
            {
              "ty": "gr",
              "it": [
                {
                  "ty": "gr",
                  "it": [
                    {
                      "ind": 0,
                      "ty": "sh",
                      "ks": {
                        "a": 0,
                        "k": {
                          "i": [
                            [0, 0],
                            [0, 0]
                          ],
                          "o": [
                            [0, 0],
                            [0, 0]
                          ],
                          "v": [
                            [0.52, 7.673],
                            [0.52, 13.462]
                          ],
                          "c": false
                        }
                      },
                      "nm": "P"
                    },
                    {
                      "ty": "st",
                      "c": { "a": 0, "k": [0.243, 0.204, 0.49, 1] },
                      "o": { "a": 0, "k": 100 },
                      "w": { "a": 0, "k": 0.5 },
                      "lc": 2,
                      "lj": 2,
                      "nm": "S"
                    },
                    {
                      "ty": "fl",
                      "c": { "a": 0, "k": [1, 1, 1, 1] },
                      "o": { "a": 0, "k": 100 },
                      "r": 1,
                      "nm": "F"
                    },
                    {
                      "ty": "tr",
                      "p": { "a": 0, "k": [0, 0] },
                      "a": { "a": 0, "k": [0, 0] },
                      "s": { "a": 0, "k": [100, 100] },
                      "r": { "a": 0, "k": 0 },
                      "o": { "a": 0, "k": 100 },
                      "sk": { "a": 0, "k": 0 },
                      "sa": { "a": 0, "k": 0 },
                      "nm": "T"
                    }
                  ],
                  "nm": "G"
                },
                {
                  "ty": "tr",
                  "p": { "a": 0, "k": [0, 0] },
                  "a": { "a": 0, "k": [0, 0] },
                  "s": { "a": 0, "k": [100, 100] },
                  "r": { "a": 0, "k": 0 },
                  "o": { "a": 0, "k": 100 },
                  "sk": { "a": 0, "k": 0 },
                  "sa": { "a": 0, "k": 0 },
                  "nm": "T"
                }
              ],
              "nm": "G"
            },
            {
              "ty": "tr",
              "p": { "a": 0, "k": [0, 0] },
              "a": { "a": 0, "k": [0, 0] },
              "s": { "a": 0, "k": [100, 100] },
              "r": { "a": 0, "k": 0 },
              "o": { "a": 0, "k": 100 },
              "sk": { "a": 0, "k": 0 },
              "sa": { "a": 0, "k": 0 },
              "nm": "T"
            }
          ],
          "nm": "G"
        }
      ],
      "ip": 0,
      "op": 90,
      "st": 0
    },
    {
      "ind": 7,
      "ty": 4,
      "nm": "c",
      "parent": 1,
      "sr": 1,
      "ks": {
        "o": { "a": 0, "k": 100 },
        "r": { "a": 0, "k": 0 },
        "p": { "a": 0, "k": [50, 70.756, 0], "l": 2 },
        "a": { "a": 0, "k": [0, 20.756, 0], "l": 2 },
        "s": {
          "a": 1,
          "k": [
            {
              "i": { "x": [0.667, 0.667, 0.667], "y": [1, 1, 1] },
              "o": { "x": [0.333, 0.333, 0.333], "y": [0, 0, 0] },
              "t": 0,
              "s": [100, 100, 100]
            },
            {
              "i": { "x": [0.667, 0.667, 0.667], "y": [1, 1, 1] },
              "o": { "x": [0.333, 0.333, 0.333], "y": [0, 0, 0] },
              "t": 7.5,
              "s": [102, 98, 100]
            },
            {
              "i": { "x": [0.667, 0.667, 0.667], "y": [1, 1, 1] },
              "o": { "x": [0.333, 0.333, 0.333], "y": [0, 0, 0] },
              "t": 15,
              "s": [98, 102, 100]
            },
            {
              "i": { "x": [0.667, 0.667, 0.667], "y": [1, 1, 1] },
              "o": { "x": [0.333, 0.333, 0.333], "y": [0, 0, 0] },
              "t": 22.5,
              "s": [102, 98, 100]
            },
            {
              "i": { "x": [0.667, 0.667, 0.667], "y": [1, 1, 1] },
              "o": { "x": [0.333, 0.333, 0.333], "y": [0, 0, 0] },
              "t": 30,
              "s": [100, 100, 100]
            },
            {
              "i": { "x": [0.667, 0.667, 0.667], "y": [1, 1, 1] },
              "o": { "x": [0.333, 0.333, 0.333], "y": [0, 0, 0] },
              "t": 37.5,
              "s": [102, 98, 100]
            },
            {
              "i": { "x": [0.667, 0.667, 0.667], "y": [1, 1, 1] },
              "o": { "x": [0.333, 0.333, 0.333], "y": [0, 0, 0] },
              "t": 45,
              "s": [98, 102, 100]
            },
            {
              "i": { "x": [0.667, 0.667, 0.667], "y": [1, 1, 1] },
              "o": { "x": [0.333, 0.333, 0.333], "y": [0, 0, 0] },
              "t": 52.5,
              "s": [102, 98, 100]
            },
            { "t": 60, "s": [100, 100, 100] }
          ],
          "l": 2
        }
      },
      "ao": 0,
      "shapes": [
        {
          "ty": "gr",
          "it": [
            {
              "ty": "st",
              "c": { "a": 0, "k": [0.243, 0.204, 0.49, 1] },
              "o": { "a": 0, "k": 100 },
              "w": { "a": 0, "k": 0.5 },
              "lc": 2,
              "lj": 2,
              "nm": "S"
            },
            {
              "ty": "fl",
              "c": { "a": 0, "k": [1, 1, 1, 1] },
              "o": { "a": 0, "k": 100 },
              "r": 1,
              "nm": "F"
            },
            {
              "ty": "tr",
              "p": { "a": 0, "k": [0, 0] },
              "a": { "a": 0, "k": [0, 0] },
              "s": { "a": 0, "k": [100, 100] },
              "r": { "a": 0, "k": 0 },
              "o": { "a": 0, "k": 100 },
              "sk": { "a": 0, "k": 0 },
              "sa": { "a": 0, "k": 0 },
              "nm": "T"
            }
          ],
          "nm": "G"
        },
        {
          "ty": "gr",
          "it": [
            {
              "ty": "gr",
              "it": [
                {
                  "ty": "gr",
                  "it": [
                    {
                      "ty": "st",
                      "c": { "a": 0, "k": [0.243, 0.204, 0.49, 1] },
                      "o": { "a": 0, "k": 100 },
                      "w": { "a": 0, "k": 0.5 },
                      "lc": 2,
                      "lj": 2,
                      "nm": "S"
                    },
                    {
                      "ty": "fl",
                      "c": { "a": 0, "k": [0.949, 0.576, 0.122, 1] },
                      "o": { "a": 0, "k": 100 },
                      "r": 1,
                      "nm": "F"
                    },
                    {
                      "ty": "tr",
                      "p": { "a": 0, "k": [0, 0] },
                      "a": { "a": 0, "k": [0, 0] },
                      "s": { "a": 0, "k": [100, 100] },
                      "r": { "a": 0, "k": 0 },
                      "o": { "a": 0, "k": 100 },
                      "sk": { "a": 0, "k": 0 },
                      "sa": { "a": 0, "k": 0 },
                      "nm": "T"
                    }
                  ],
                  "nm": "G"
                },
                {
                  "ty": "gr",
                  "it": [
                    {
                      "ty": "st",
                      "c": { "a": 0, "k": [0.243, 0.204, 0.49, 1] },
                      "o": { "a": 0, "k": 100 },
                      "w": { "a": 0, "k": 0.5 },
                      "lc": 2,
                      "lj": 2,
                      "nm": "S"
                    },
                    {
                      "ty": "fl",
                      "c": { "a": 0, "k": [1, 1, 1, 1] },
                      "o": { "a": 0, "k": 100 },
                      "r": 1,
                      "nm": "F"
                    },
                    {
                      "ty": "tr",
                      "p": { "a": 0, "k": [0, 0] },
                      "a": { "a": 0, "k": [0, 0] },
                      "s": { "a": 0, "k": [100, 100] },
                      "r": { "a": 0, "k": 0 },
                      "o": { "a": 0, "k": 100 },
                      "sk": { "a": 0, "k": 0 },
                      "sa": { "a": 0, "k": 0 },
                      "nm": "T"
                    }
                  ],
                  "nm": "G"
                },
                {
                  "ty": "tr",
                  "p": { "a": 0, "k": [0, 0] },
                  "a": { "a": 0, "k": [0, 0] },
                  "s": { "a": 0, "k": [100, 100] },
                  "r": { "a": 0, "k": 0 },
                  "o": { "a": 0, "k": 100 },
                  "sk": { "a": 0, "k": 0 },
                  "sa": { "a": 0, "k": 0 },
                  "nm": "T"
                }
              ],
              "nm": "G"
            },
            {
              "ty": "gr",
              "it": [
                {
                  "ind": 0,
                  "ty": "sh",
                  "ks": {
                    "a": 0,
                    "k": {
                      "i": [
                        [0, -2.121],
                        [2.121, 0],
                        [0, 2.121],
                        [-2.121, 0]
                      ],
                      "o": [
                        [0, 2.121],
                        [-2.121, 0],
                        [0, -2.121],
                        [2.121, 0]
                      ],
                      "v": [
                        [4.361, 7.673],
                        [0.52, 11.514],
                        [-3.321, 7.673],
                        [0.52, 3.833]
                      ],
                      "c": true
                    }
                  },
                  "nm": "P"
                },
                {
                  "ty": "st",
                  "c": { "a": 0, "k": [0.243, 0.204, 0.49, 1] },
                  "o": { "a": 0, "k": 100 },
                  "w": { "a": 0, "k": 0.5 },
                  "lc": 2,
                  "lj": 2,
                  "nm": "S"
                },
                {
                  "ty": "fl",
                  "c": { "a": 0, "k": [1, 1, 1, 1] },
                  "o": { "a": 0, "k": 100 },
                  "r": 1,
                  "nm": "F"
                },
                {
                  "ty": "tr",
                  "p": { "a": 0, "k": [0, 0] },
                  "a": { "a": 0, "k": [0, 0] },
                  "s": { "a": 0, "k": [100, 100] },
                  "r": { "a": 0, "k": 0 },
                  "o": { "a": 0, "k": 100 },
                  "sk": { "a": 0, "k": 0 },
                  "sa": { "a": 0, "k": 0 },
                  "nm": "T"
                }
              ],
              "nm": "G"
            },
            {
              "ty": "gr",
              "it": [
                {
                  "ind": 0,
                  "ty": "sh",
                  "ks": {
                    "a": 0,
                    "k": {
                      "i": [
                        [0, -0.882],
                        [0, 0],
                        [0.882, 0],
                        [0, 0],
                        [0, 1.762],
                        [0, 0],
                        [-0.741, 0],
                        [0, 0],
                        [-0.174, -0.562],
                        [0, 0],
                        [0, 0]
                      ],
                      "o": [
                        [0, 0],
                        [0, 0.882],
                        [0, 0],
                        [-1.762, 0],
                        [0, 0],
                        [0, -0.741],
                        [0, 0],
                        [0.588, 0],
                        [0, 0],
                        [0, 0],
                        [0.882, 0]
                      ],
                      "v": [
                        [-6.841, -15.482],
                        [-6.841, -15.482],
                        [-8.438, -13.885],
                        [-14.511, -13.885],
                        [-17.702, -17.076],
                        [-17.702, -18.959],
                        [-16.361, -20.301],
                        [-16.361, -20.301],
                        [-15.079, -19.357],
                        [-14.373, -17.079],
                        [-8.438, -17.079]
                      ],
                      "c": true
                    }
                  },
                  "nm": "P"
                },
                {
                  "ty": "st",
                  "c": { "a": 0, "k": [0.243, 0.204, 0.49, 1] },
                  "o": { "a": 0, "k": 100 },
                  "w": { "a": 0, "k": 0.5 },
                  "lc": 2,
                  "lj": 2,
                  "nm": "S"
                },
                {
                  "ty": "fl",
                  "c": { "a": 0, "k": [0.949, 0.576, 0.122, 1] },
                  "o": { "a": 0, "k": 100 },
                  "r": 1,
                  "nm": "F"
                },
                {
                  "ty": "tr",
                  "p": { "a": 0, "k": [0, 0] },
                  "a": { "a": 0, "k": [0, 0] },
                  "s": { "a": 0, "k": [100, 100] },
                  "r": { "a": 0, "k": 0 },
                  "o": { "a": 0, "k": 100 },
                  "sk": { "a": 0, "k": 0 },
                  "sa": { "a": 0, "k": 0 },
                  "nm": "T"
                }
              ],
              "nm": "G"
            },
            {
              "ty": "gr",
              "it": [
                {
                  "ind": 0,
                  "ty": "sh",
                  "ks": {
                    "a": 0,
                    "k": {
                      "i": [
                        [0, 0],
                        [0, 0],
                        [0, 0],
                        [0.485, -0.301],
                        [-0.299, -0.483]
                      ],
                      "o": [
                        [0, 0],
                        [0, 0],
                        [-0.298, -0.484],
                        [-0.484, 0.299],
                        [0, 0]
                      ],
                      "v": [
                        [-12.681, -12.588],
                        [-10.261, -12.588],
                        [-11.395, -14.426],
                        [-12.812, -14.761],
                        [-13.147, -13.344]
                      ],
                      "c": true
                    }
                  },
                  "nm": "P"
                },
                {
                  "ty": "st",
                  "c": { "a": 0, "k": [0.243, 0.204, 0.49, 1] },
                  "o": { "a": 0, "k": 100 },
                  "w": { "a": 0, "k": 0.5 },
                  "lc": 2,
                  "lj": 2,
                  "nm": "S"
                },
                {
                  "ty": "fl",
                  "c": { "a": 0, "k": [0.243, 0.204, 0.49, 1] },
                  "o": { "a": 0, "k": 100 },
                  "r": 1,
                  "nm": "F"
                },
                {
                  "ty": "tr",
                  "p": { "a": 0, "k": [0, 0] },
                  "a": { "a": 0, "k": [0, 0] },
                  "s": { "a": 0, "k": [100, 100] },
                  "r": { "a": 0, "k": 0 },
                  "o": { "a": 0, "k": 100 },
                  "sk": { "a": 0, "k": 0 },
                  "sa": { "a": 0, "k": 0 },
                  "nm": "T"
                }
              ],
              "nm": "G"
            },
            {
              "ty": "gr",
              "it": [
                {
                  "ind": 0,
                  "ty": "sh",
                  "ks": {
                    "a": 0,
                    "k": {
                      "i": [
                        [0, 0],
                        [0, 0],
                        [0, 0]
                      ],
                      "o": [
                        [0, 0],
                        [0, 0],
                        [0, 0]
                      ],
                      "v": [
                        [0.944, 5.56],
                        [-8.187, -9.23],
                        [8.334, -9.23]
                      ],
                      "c": true
                    }
                  },
                  "nm": "P"
                },
                {
                  "ind": 1,
                  "ty": "sh",
                  "ks": {
                    "a": 0,
                    "k": {
                      "i": [
                        [0, 0],
                        [0, 0],
                        [0, 0]
                      ],
                      "o": [
                        [0, 0],
                        [0, 0],
                        [0, 0]
                      ],
                      "v": [
                        [-9.896, -8.078],
                        [-0.806, 6.644],
                        [-17.253, 6.644]
                      ],
                      "c": true
                    }
                  },
                  "nm": "P"
                },
                {
                  "ind": 2,
                  "ty": "sh",
                  "ks": {
                    "a": 0,
                    "k": {
                      "i": [
                        [0.188, 0.303],
                        [0.357, 0],
                        [0, 0],
                        [0, 0],
                        [0.485, -0.301],
                        [-0.299, -0.483],
                        [0, 0],
                        [0, 0],
                        [-0.188, -0.303],
                        [-0.357, 0],
                        [0, 0],
                        [0, 0],
                        [0, 0],
                        [-0.092, 0.026],
                        [-0.135, 0.173],
                        [-0.018, 0.028],
                        [-0.016, 0.032],
                        [0, 0]
                      ],
                      "o": [
                        [-0.188, -0.304],
                        [0, 0],
                        [0, 0],
                        [-0.298, -0.484],
                        [-0.484, 0.299],
                        [0, 0],
                        [0, 0],
                        [-0.16, 0.32],
                        [0.188, 0.304],
                        [0, 0],
                        [0, 0],
                        [0, 0],
                        [0.093, 0],
                        [0.21, -0.06],
                        [0.021, -0.026],
                        [0.019, -0.029],
                        [0, 0],
                        [0.16, -0.32]
                      ],
                      "v": [
                        [10.876, -10.801],
                        [10, -11.29],
                        [-9.459, -11.29],
                        [-11.395, -14.426],
                        [-12.812, -14.761],
                        [-13.147, -13.344],
                        [-11.169, -10.14],
                        [-19.84, 7.213],
                        [-19.794, 8.214],
                        [-18.918, 8.703],
                        [1.04, 8.703],
                        [1.04, 8.703],
                        [1.041, 8.703],
                        [1.32, 8.664],
                        [1.846, 8.301],
                        [1.902, 8.22],
                        [1.961, 8.134],
                        [10.921, -9.799]
                      ],
                      "c": true
                    }
                  },
                  "nm": "P"
                },
                {
                  "ty": "st",
                  "c": { "a": 0, "k": [0.243, 0.204, 0.49, 1] },
                  "o": { "a": 0, "k": 100 },
                  "w": { "a": 0, "k": 0.5 },
                  "lc": 2,
                  "lj": 2,
                  "nm": "S"
                },
                {
                  "ty": "fl",
                  "c": { "a": 0, "k": [0.753, 0.847, 0.925, 1] },
                  "o": { "a": 0, "k": 100 },
                  "r": 1,
                  "nm": "F"
                },
                {
                  "ty": "tr",
                  "p": { "a": 0, "k": [0, 0] },
                  "a": { "a": 0, "k": [0, 0] },
                  "s": { "a": 0, "k": [100, 100] },
                  "r": { "a": 0, "k": 0 },
                  "o": { "a": 0, "k": 100 },
                  "sk": { "a": 0, "k": 0 },
                  "sa": { "a": 0, "k": 0 },
                  "nm": "T"
                }
              ],
              "nm": "G"
            },
            {
              "ty": "gr",
              "it": [
                {
                  "ty": "gr",
                  "it": [
                    {
                      "ind": 0,
                      "ty": "sh",
                      "ks": {
                        "a": 0,
                        "k": {
                          "i": [
                            [0.118, 0],
                            [0.153, 0.417],
                            [0, 0],
                            [0, 0],
                            [0, 0.569],
                            [-0.569, 0],
                            [0, 0],
                            [-0.149, -0.405],
                            [0, 0],
                            [0.534, -0.196]
                          ],
                          "o": [
                            [-0.419, 0],
                            [0, 0],
                            [0, 0],
                            [-0.569, 0],
                            [0, -0.569],
                            [0, 0],
                            [0.431, 0],
                            [0, 0],
                            [0.196, 0.534],
                            [-0.117, 0.043]
                          ],
                          "v": [
                            [18.918, 8.703],
                            [17.951, 8.028],
                            [8.13, -18.696],
                            [2.822, -18.696],
                            [1.792, -19.726],
                            [2.822, -20.756],
                            [8.849, -20.756],
                            [9.816, -20.081],
                            [19.884, 7.318],
                            [19.273, 8.64]
                          ],
                          "c": true
                        }
                      },
                      "nm": "P"
                    },
                    {
                      "ty": "st",
                      "c": { "a": 0, "k": [0.243, 0.204, 0.49, 1] },
                      "o": { "a": 0, "k": 100 },
                      "w": { "a": 0, "k": 0.5 },
                      "lc": 2,
                      "lj": 2,
                      "nm": "S"
                    },
                    {
                      "ty": "fl",
                      "c": { "a": 0, "k": [0.753, 0.847, 0.925, 1] },
                      "o": { "a": 0, "k": 100 },
                      "r": 1,
                      "nm": "F"
                    },
                    {
                      "ty": "tr",
                      "p": { "a": 0, "k": [0, 0] },
                      "a": { "a": 0, "k": [0, 0] },
                      "s": { "a": 0, "k": [100, 100] },
                      "r": { "a": 0, "k": 0 },
                      "o": { "a": 0, "k": 100 },
                      "sk": { "a": 0, "k": 0 },
                      "sa": { "a": 0, "k": 0 },
                      "nm": "T"
                    }
                  ],
                  "nm": "G"
                },
                {
                  "ty": "tr",
                  "p": { "a": 0, "k": [0, 0] },
                  "a": { "a": 0, "k": [0, 0] },
                  "s": { "a": 0, "k": [100, 100] },
                  "r": { "a": 0, "k": 0 },
                  "o": { "a": 0, "k": 100 },
                  "sk": { "a": 0, "k": 0 },
                  "sa": { "a": 0, "k": 0 },
                  "nm": "T"
                }
              ],
              "nm": "G"
            },
            {
              "ty": "gr",
              "it": [
                {
                  "ind": 0,
                  "ty": "sh",
                  "ks": {
                    "a": 0,
                    "k": {
                      "i": [
                        [0, -2.121],
                        [2.121, 0],
                        [0, 2.121],
                        [-2.121, 0]
                      ],
                      "o": [
                        [0, 2.121],
                        [-2.121, 0],
                        [0, -2.121],
                        [2.121, 0]
                      ],
                      "v": [
                        [-15.077, 7.673],
                        [-18.918, 11.514],
                        [-22.759, 7.673],
                        [-18.918, 3.833]
                      ],
                      "c": true
                    }
                  },
                  "nm": "P"
                },
                {
                  "ty": "st",
                  "c": { "a": 0, "k": [0.243, 0.204, 0.49, 1] },
                  "o": { "a": 0, "k": 100 },
                  "w": { "a": 0, "k": 0.5 },
                  "lc": 2,
                  "lj": 2,
                  "nm": "S"
                },
                {
                  "ty": "fl",
                  "c": { "a": 0, "k": [1, 1, 1, 1] },
                  "o": { "a": 0, "k": 100 },
                  "r": 1,
                  "nm": "F"
                },
                {
                  "ty": "tr",
                  "p": { "a": 0, "k": [0, 0] },
                  "a": { "a": 0, "k": [0, 0] },
                  "s": { "a": 0, "k": [100, 100] },
                  "r": { "a": 0, "k": 0 },
                  "o": { "a": 0, "k": 100 },
                  "sk": { "a": 0, "k": 0 },
                  "sa": { "a": 0, "k": 0 },
                  "nm": "T"
                }
              ],
              "nm": "G"
            },
            {
              "ty": "gr",
              "it": [
                {
                  "ind": 0,
                  "ty": "sh",
                  "ks": {
                    "a": 0,
                    "k": {
                      "i": [
                        [0, -5.953],
                        [5.953, 0],
                        [0, 5.953],
                        [-5.953, 0]
                      ],
                      "o": [
                        [0, 5.953],
                        [-5.953, 0],
                        [0, -5.953],
                        [5.953, 0]
                      ],
                      "v": [
                        [-8.139, 7.673],
                        [-18.918, 18.453],
                        [-29.697, 7.673],
                        [-18.918, -3.106]
                      ],
                      "c": true
                    }
                  },
                  "nm": "P"
                },
                {
                  "ty": "st",
                  "c": { "a": 0, "k": [0.243, 0.204, 0.49, 1] },
                  "o": { "a": 0, "k": 100 },
                  "w": { "a": 0, "k": 0.5 },
                  "lc": 2,
                  "lj": 2,
                  "nm": "S"
                },
                {
                  "ty": "fl",
                  "c": { "a": 0, "k": [1, 1, 1, 1] },
                  "o": { "a": 0, "k": 100 },
                  "r": 1,
                  "nm": "F"
                },
                {
                  "ty": "tr",
                  "p": { "a": 0, "k": [0, 0] },
                  "a": { "a": 0, "k": [0, 0] },
                  "s": { "a": 0, "k": [100, 100] },
                  "r": { "a": 0, "k": 0 },
                  "o": { "a": 0, "k": 100 },
                  "sk": { "a": 0, "k": 0 },
                  "sa": { "a": 0, "k": 0 },
                  "nm": "T"
                }
              ],
              "nm": "G"
            },
            {
              "ty": "gr",
              "it": [
                {
                  "ind": 0,
                  "ty": "sh",
                  "ks": {
                    "a": 0,
                    "k": {
                      "i": [
                        [0, -7.225],
                        [7.225, 0],
                        [0, 7.225],
                        [-7.225, 0]
                      ],
                      "o": [
                        [0, 7.225],
                        [-7.225, 0],
                        [0, -7.225],
                        [7.225, 0]
                      ],
                      "v": [
                        [-5.836, 7.673],
                        [-18.918, 20.756],
                        [-32, 7.673],
                        [-18.918, -5.409]
                      ],
                      "c": true
                    }
                  },
                  "nm": "P"
                },
                {
                  "ty": "st",
                  "c": { "a": 0, "k": [0.243, 0.204, 0.49, 1] },
                  "o": { "a": 0, "k": 100 },
                  "w": { "a": 0, "k": 0.5 },
                  "lc": 2,
                  "lj": 2,
                  "nm": "S"
                },
                {
                  "ty": "fl",
                  "c": { "a": 0, "k": [0.369, 0.384, 0.651, 1] },
                  "o": { "a": 0, "k": 100 },
                  "r": 1,
                  "nm": "F"
                },
                {
                  "ty": "tr",
                  "p": { "a": 0, "k": [0, 0] },
                  "a": { "a": 0, "k": [0, 0] },
                  "s": { "a": 0, "k": [100, 100] },
                  "r": { "a": 0, "k": 0 },
                  "o": { "a": 0, "k": 100 },
                  "sk": { "a": 0, "k": 0 },
                  "sa": { "a": 0, "k": 0 },
                  "nm": "T"
                }
              ],
              "nm": "G"
            },
            {
              "ty": "gr",
              "it": [
                {
                  "ind": 0,
                  "ty": "sh",
                  "ks": {
                    "a": 0,
                    "k": {
                      "i": [
                        [0, -2.121],
                        [2.121, 0],
                        [0, 2.121],
                        [-2.121, 0]
                      ],
                      "o": [
                        [0, 2.121],
                        [-2.121, 0],
                        [0, -2.121],
                        [2.121, 0]
                      ],
                      "v": [
                        [22.759, 7.673],
                        [18.918, 11.514],
                        [15.077, 7.673],
                        [18.918, 3.833]
                      ],
                      "c": true
                    }
                  },
                  "nm": "P"
                },
                {
                  "ty": "st",
                  "c": { "a": 0, "k": [0.243, 0.204, 0.49, 1] },
                  "o": { "a": 0, "k": 100 },
                  "w": { "a": 0, "k": 0.5 },
                  "lc": 2,
                  "lj": 2,
                  "nm": "S"
                },
                {
                  "ty": "fl",
                  "c": { "a": 0, "k": [1, 1, 1, 1] },
                  "o": { "a": 0, "k": 100 },
                  "r": 1,
                  "nm": "F"
                },
                {
                  "ty": "tr",
                  "p": { "a": 0, "k": [0, 0] },
                  "a": { "a": 0, "k": [0, 0] },
                  "s": { "a": 0, "k": [100, 100] },
                  "r": { "a": 0, "k": 0 },
                  "o": { "a": 0, "k": 100 },
                  "sk": { "a": 0, "k": 0 },
                  "sa": { "a": 0, "k": 0 },
                  "nm": "T"
                }
              ],
              "nm": "G"
            },
            {
              "ty": "gr",
              "it": [
                {
                  "ind": 0,
                  "ty": "sh",
                  "ks": {
                    "a": 0,
                    "k": {
                      "i": [
                        [0, -5.953],
                        [5.953, 0],
                        [0, 5.953],
                        [-5.953, 0]
                      ],
                      "o": [
                        [0, 5.953],
                        [-5.953, 0],
                        [0, -5.953],
                        [5.953, 0]
                      ],
                      "v": [
                        [29.697, 7.673],
                        [18.918, 18.453],
                        [8.139, 7.673],
                        [18.918, -3.106]
                      ],
                      "c": true
                    }
                  },
                  "nm": "P"
                },
                {
                  "ty": "st",
                  "c": { "a": 0, "k": [0.243, 0.204, 0.49, 1] },
                  "o": { "a": 0, "k": 100 },
                  "w": { "a": 0, "k": 0.5 },
                  "lc": 2,
                  "lj": 2,
                  "nm": "S"
                },
                {
                  "ty": "fl",
                  "c": { "a": 0, "k": [1, 1, 1, 1] },
                  "o": { "a": 0, "k": 100 },
                  "r": 1,
                  "nm": "F"
                },
                {
                  "ty": "tr",
                  "p": { "a": 0, "k": [0, 0] },
                  "a": { "a": 0, "k": [0, 0] },
                  "s": { "a": 0, "k": [100, 100] },
                  "r": { "a": 0, "k": 0 },
                  "o": { "a": 0, "k": 100 },
                  "sk": { "a": 0, "k": 0 },
                  "sa": { "a": 0, "k": 0 },
                  "nm": "T"
                }
              ],
              "nm": "G"
            },
            {
              "ty": "gr",
              "it": [
                {
                  "ind": 0,
                  "ty": "sh",
                  "ks": {
                    "a": 0,
                    "k": {
                      "i": [
                        [0, -7.225],
                        [7.225, 0],
                        [0, 7.225],
                        [-7.225, 0]
                      ],
                      "o": [
                        [0, 7.225],
                        [-7.225, 0],
                        [0, -7.225],
                        [7.225, 0]
                      ],
                      "v": [
                        [32, 7.673],
                        [18.918, 20.756],
                        [5.836, 7.673],
                        [18.918, -5.409]
                      ],
                      "c": true
                    }
                  },
                  "nm": "P"
                },
                {
                  "ty": "st",
                  "c": { "a": 0, "k": [0.243, 0.204, 0.49, 1] },
                  "o": { "a": 0, "k": 100 },
                  "w": { "a": 0, "k": 0.5 },
                  "lc": 2,
                  "lj": 2,
                  "nm": "S"
                },
                {
                  "ty": "fl",
                  "c": { "a": 0, "k": [0.369, 0.384, 0.651, 1] },
                  "o": { "a": 0, "k": 100 },
                  "r": 1,
                  "nm": "F"
                },
                {
                  "ty": "tr",
                  "p": { "a": 0, "k": [0, 0] },
                  "a": { "a": 0, "k": [0, 0] },
                  "s": { "a": 0, "k": [100, 100] },
                  "r": { "a": 0, "k": 0 },
                  "o": { "a": 0, "k": 100 },
                  "sk": { "a": 0, "k": 0 },
                  "sa": { "a": 0, "k": 0 },
                  "nm": "T"
                }
              ],
              "nm": "G"
            },
            {
              "ty": "gr",
              "it": [
                {
                  "ty": "gr",
                  "it": [
                    {
                      "ty": "st",
                      "c": { "a": 0, "k": [0.243, 0.204, 0.49, 1] },
                      "o": { "a": 0, "k": 100 },
                      "w": { "a": 0, "k": 0.5 },
                      "lc": 2,
                      "lj": 2,
                      "nm": "S"
                    },
                    {
                      "ty": "fl",
                      "c": { "a": 0, "k": [0.949, 0.576, 0.122, 1] },
                      "o": { "a": 0, "k": 100 },
                      "r": 1,
                      "nm": "F"
                    },
                    {
                      "ty": "tr",
                      "p": { "a": 0, "k": [0, 0] },
                      "a": { "a": 0, "k": [0, 0] },
                      "s": { "a": 0, "k": [100, 100] },
                      "r": { "a": 0, "k": 0 },
                      "o": { "a": 0, "k": 100 },
                      "sk": { "a": 0, "k": 0 },
                      "sa": { "a": 0, "k": 0 },
                      "nm": "T"
                    }
                  ],
                  "nm": "G"
                },
                {
                  "ty": "gr",
                  "it": [
                    {
                      "ty": "st",
                      "c": { "a": 0, "k": [0.243, 0.204, 0.49, 1] },
                      "o": { "a": 0, "k": 100 },
                      "w": { "a": 0, "k": 0.5 },
                      "lc": 2,
                      "lj": 2,
                      "nm": "S"
                    },
                    {
                      "ty": "fl",
                      "c": { "a": 0, "k": [1, 1, 1, 1] },
                      "o": { "a": 0, "k": 100 },
                      "r": 1,
                      "nm": "F"
                    },
                    {
                      "ty": "tr",
                      "p": { "a": 0, "k": [0, 0] },
                      "a": { "a": 0, "k": [0, 0] },
                      "s": { "a": 0, "k": [100, 100] },
                      "r": { "a": 0, "k": 0 },
                      "o": { "a": 0, "k": 100 },
                      "sk": { "a": 0, "k": 0 },
                      "sa": { "a": 0, "k": 0 },
                      "nm": "T"
                    }
                  ],
                  "nm": "G"
                },
                {
                  "ty": "tr",
                  "p": { "a": 0, "k": [0, 0] },
                  "a": { "a": 0, "k": [0, 0] },
                  "s": { "a": 0, "k": [100, 100] },
                  "r": { "a": 0, "k": 0 },
                  "o": { "a": 0, "k": 100 },
                  "sk": { "a": 0, "k": 0 },
                  "sa": { "a": 0, "k": 0 },
                  "nm": "T"
                }
              ],
              "nm": "G"
            },
            {
              "ty": "tr",
              "p": { "a": 0, "k": [0, 0] },
              "a": { "a": 0, "k": [0, 0] },
              "s": { "a": 0, "k": [100, 100] },
              "r": { "a": 0, "k": 0 },
              "o": { "a": 0, "k": 100 },
              "sk": { "a": 0, "k": 0 },
              "sa": { "a": 0, "k": 0 },
              "nm": "T"
            }
          ],
          "nm": "G"
        }
      ],
      "ip": 0,
      "op": 90,
      "st": 0
    },
    {
      "ind": 8,
      "ty": 4,
      "nm": "b",
      "parent": 9,
      "sr": 1,
      "ks": {
        "o": { "a": 0, "k": 100 },
        "r": {
          "a": 1,
          "k": [
            {
              "i": { "x": [0.833], "y": [0.833] },
              "o": { "x": [0.167], "y": [0.167] },
              "t": 0,
              "s": [360]
            },
            { "t": 60, "s": [0] }
          ]
        },
        "p": { "a": 0, "k": [0.52, -2.2, 0], "l": 2 },
        "a": { "a": 0, "k": [0.52, -2.2, 0], "l": 2 },
        "s": { "a": 0, "k": [100, 100, 100], "l": 2 }
      },
      "ao": 0,
      "shapes": [
        {
          "ty": "gr",
          "it": [
            {
              "ty": "gr",
              "it": [
                {
                  "ty": "gr",
                  "it": [
                    {
                      "ind": 0,
                      "ty": "sh",
                      "ks": {
                        "a": 0,
                        "k": {
                          "i": [
                            [0, 0.345],
                            [0, 0],
                            [-0.345, 0],
                            [0, 0],
                            [0, -0.358],
                            [0, 0],
                            [0.345, 0],
                            [0, 0]
                          ],
                          "o": [
                            [0, 0],
                            [0, -0.358],
                            [0, 0],
                            [0.345, 0],
                            [0, 0],
                            [0, 0.345],
                            [0, 0],
                            [-0.345, 0]
                          ],
                          "v": [
                            [-2.33, -1.719],
                            [-2.33, -2.669],
                            [-1.701, -3.31],
                            [2.74, -3.31],
                            [3.37, -2.669],
                            [3.37, -1.719],
                            [2.74, -1.09],
                            [-1.701, -1.09]
                          ],
                          "c": true
                        }
                      },
                      "nm": "P"
                    },
                    {
                      "ty": "st",
                      "c": { "a": 0, "k": [0.243, 0.204, 0.49, 1] },
                      "o": { "a": 0, "k": 100 },
                      "w": { "a": 0, "k": 0.5 },
                      "lc": 2,
                      "lj": 2,
                      "nm": "S"
                    },
                    {
                      "ty": "fl",
                      "c": { "a": 0, "k": [0.949, 0.576, 0.122, 1] },
                      "o": { "a": 0, "k": 100 },
                      "r": 1,
                      "nm": "F"
                    },
                    {
                      "ty": "tr",
                      "p": { "a": 0, "k": [0, 0] },
                      "a": { "a": 0, "k": [0, 0] },
                      "s": { "a": 0, "k": [100, 100] },
                      "r": { "a": 0, "k": 0 },
                      "o": { "a": 0, "k": 100 },
                      "sk": { "a": 0, "k": 0 },
                      "sa": { "a": 0, "k": 0 },
                      "nm": "T"
                    }
                  ],
                  "nm": "G"
                },
                {
                  "ty": "tr",
                  "p": { "a": 0, "k": [0, 0] },
                  "a": { "a": 0, "k": [0, 0] },
                  "s": { "a": 0, "k": [100, 100] },
                  "r": { "a": 0, "k": 0 },
                  "o": { "a": 0, "k": 100 },
                  "sk": { "a": 0, "k": 0 },
                  "sa": { "a": 0, "k": 0 },
                  "nm": "T"
                }
              ],
              "nm": "G"
            },
            {
              "ty": "tr",
              "p": { "a": 0, "k": [0, 0] },
              "a": { "a": 0, "k": [0, 0] },
              "s": { "a": 0, "k": [100, 100] },
              "r": { "a": 0, "k": 0 },
              "o": { "a": 0, "k": 100 },
              "sk": { "a": 0, "k": 0 },
              "sa": { "a": 0, "k": 0 },
              "nm": "T"
            }
          ],
          "nm": "G"
        }
      ],
      "ip": 0,
      "op": 90,
      "st": 0
    },
    {
      "ind": 9,
      "ty": 4,
      "nm": "l",
      "parent": 7,
      "sr": 1,
      "ks": {
        "o": { "a": 0, "k": 100 },
        "r": {
          "a": 1,
          "k": [
            {
              "i": { "x": [0.833], "y": [0.833] },
              "o": { "x": [0.167], "y": [0.167] },
              "t": 0,
              "s": [0]
            },
            { "t": 60, "s": [360] }
          ]
        },
        "p": { "a": 0, "k": [0.52, 4.7, 0], "l": 2 },
        "a": { "a": 0, "k": [0.52, 4.7, 0], "l": 2 },
        "s": { "a": 0, "k": [100, 100, 100], "l": 2 }
      },
      "ao": 0,
      "shapes": [
        {
          "ty": "gr",
          "it": [
            {
              "ty": "gr",
              "it": [
                {
                  "ty": "gr",
                  "it": [
                    {
                      "ind": 0,
                      "ty": "sh",
                      "ks": {
                        "a": 0,
                        "k": {
                          "i": [
                            [0, 0],
                            [0, 0]
                          ],
                          "o": [
                            [0, 0],
                            [0, 0]
                          ],
                          "v": [
                            [0.52, 4.7],
                            [0.52, -1.088]
                          ],
                          "c": false
                        }
                      },
                      "nm": "P"
                    },
                    {
                      "ty": "st",
                      "c": { "a": 0, "k": [0.243, 0.204, 0.49, 1] },
                      "o": { "a": 0, "k": 100 },
                      "w": { "a": 0, "k": 0.5 },
                      "lc": 2,
                      "lj": 2,
                      "nm": "S"
                    },
                    {
                      "ty": "fl",
                      "c": { "a": 0, "k": [1, 1, 1, 1] },
                      "o": { "a": 0, "k": 100 },
                      "r": 1,
                      "nm": "F"
                    },
                    {
                      "ty": "tr",
                      "p": { "a": 0, "k": [0, 0] },
                      "a": { "a": 0, "k": [0, 0] },
                      "s": { "a": 0, "k": [100, 100] },
                      "r": { "a": 0, "k": 0 },
                      "o": { "a": 0, "k": 100 },
                      "sk": { "a": 0, "k": 0 },
                      "sa": { "a": 0, "k": 0 },
                      "nm": "T"
                    }
                  ],
                  "nm": "G"
                },
                {
                  "ty": "tr",
                  "p": { "a": 0, "k": [0, 0] },
                  "a": { "a": 0, "k": [0, 0] },
                  "s": { "a": 0, "k": [100, 100] },
                  "r": { "a": 0, "k": 0 },
                  "o": { "a": 0, "k": 100 },
                  "sk": { "a": 0, "k": 0 },
                  "sa": { "a": 0, "k": 0 },
                  "nm": "T"
                }
              ],
              "nm": "G"
            },
            {
              "ty": "tr",
              "p": { "a": 0, "k": [0, 0] },
              "a": { "a": 0, "k": [0, 0] },
              "s": { "a": 0, "k": [100, 100] },
              "r": { "a": 0, "k": 0 },
              "o": { "a": 0, "k": 100 },
              "sk": { "a": 0, "k": 0 },
              "sa": { "a": 0, "k": 0 },
              "nm": "T"
            }
          ],
          "nm": "G"
        }
      ],
      "ip": 0,
      "op": 90,
      "st": 0
    },
    {
      "ind": 10,
      "ty": 4,
      "nm": "f",
      "parent": 1,
      "sr": 1,
      "ks": {
        "o": { "a": 0, "k": 100 },
        "r": { "a": 0, "k": 0 },
        "p": { "a": 0, "k": [44.253, 70.756, 0], "l": 2 },
        "a": { "a": 0, "k": [-5.747, 20.756, 0], "l": 2 },
        "s": { "a": 0, "k": [100, 100, 100], "l": 2 }
      },
      "ao": 0,
      "shapes": [
        {
          "ty": "gr",
          "it": [
            {
              "ind": 0,
              "ty": "sh",
              "ks": {
                "a": 0,
                "k": {
                  "i": [
                    [0, 0],
                    [0, 0]
                  ],
                  "o": [
                    [0, 0],
                    [0, 0]
                  ],
                  "v": [
                    [18.918, 20.756],
                    [-30.411, 20.756]
                  ],
                  "c": false
                }
              },
              "nm": "P"
            },
            {
              "ty": "st",
              "c": { "a": 0, "k": [0.243, 0.204, 0.49, 1] },
              "o": { "a": 0, "k": 100 },
              "w": { "a": 0, "k": 0.5 },
              "lc": 2,
              "lj": 2,
              "nm": "S"
            },
            {
              "ty": "fl",
              "c": { "a": 0, "k": [1, 1, 1, 1] },
              "o": { "a": 0, "k": 100 },
              "r": 1,
              "nm": "F"
            },
            {
              "ty": "tr",
              "p": { "a": 0, "k": [0, 0] },
              "a": { "a": 0, "k": [0, 0] },
              "s": { "a": 0, "k": [100, 100] },
              "r": { "a": 0, "k": 0 },
              "o": { "a": 0, "k": 100 },
              "sk": { "a": 0, "k": 0 },
              "sa": { "a": 0, "k": 0 },
              "nm": "T"
            }
          ],
          "nm": "G"
        }
      ],
      "ip": 0,
      "op": 90,
      "st": 0
    }
  ],
  "markers": []
}
